wavaugmentate/__init__.py
wavaugmentate/aug.py
wavaugmentate/mcs.py
wavaugmentate/wavaug.py
wavaugmentate-0.2.5.dist-info/LICENSE
wavaugmentate-0.2.5.dist-info/METADATA
wavaugmentate-0.2.5.dist-info/WHEEL
wavaugmentate-0.2.5.dist-info/entry_points.txt
wavaugmentate-0.2.5.dist-info/top_level.txt
wavaugmentate-0.2.5.dist-info/RECORD
