Metadata-Version: 2.2
Name: wavaugmentate
Version: 0.2.5
Summary:  The package wavaugmentate makes audio signal augmentation conversions.
Author-email: Igor Plastov <chetverovod@gmail.com>
Maintainer-email: Igor Plastov <chetverovod@gmail.com>
Project-URL: Documentation, https://wavaugmentate.readthedocs.io/en/latest/
Project-URL: Homepage, https://github.com/chetverovod/wavaugmentate
Project-URL: Issues, https://github.com/chetverovod/wavaugmentate/issues
Keywords: augmentation,WAV,ML,DL,audio,sound
Classifier: Programming Language :: Python :: 3
Classifier: License :: OSI Approved :: MIT License
Classifier: Operating System :: OS Independent
Requires-Python: >=3.9
License-File: LICENSE
